Metadata-Version: 2.1
Name: mara-schema
Version: 1.2.1
Summary: Mapping of DWH database tables to business entities, attributes & metrics in Python, with automatic creation of flattened tables
Home-page: https://github.com/mara/mara-schema
Author: Mara contributors
License: MIT
Requires-Python: >=3.6
License-File: LICENSE
Requires-Dist: flask
Requires-Dist: graphviz
Requires-Dist: mara-page
Requires-Dist: sqlalchemy
